openedx_sample_plugin-1.3.1.dist-info/licenses/LICENSE.txt
sample_plugin/__init__.py
sample_plugin/apps.py
sample_plugin/models.py
sample_plugin/pipeline.py
sample_plugin/serializers.py
sample_plugin/signals.py
sample_plugin/urls.py
sample_plugin/views.py
sample_plugin/conf/locale/config.yaml
sample_plugin/migrations/0001_initial.py
sample_plugin/migrations/__init__.py
sample_plugin/settings/common.py
sample_plugin/settings/production.py
sample_plugin/settings/test.py
sample_plugin/templates/sample_plugin/base.html
openedx_sample_plugin-1.3.1.dist-info/METADATA
openedx_sample_plugin-1.3.1.dist-info/WHEEL
openedx_sample_plugin-1.3.1.dist-info/entry_points.txt
openedx_sample_plugin-1.3.1.dist-info/top_level.txt
openedx_sample_plugin-1.3.1.dist-info/RECORD
