Metadata-Version: 2.4
Name: openedx-sample-plugin
Version: 1.3.1
Summary: A sample backend plugin for the Open edX Platform
Author-email: Open edX Project <oscm@openedx.org>
License-Expression: Apache-2.0
Project-URL: Homepage, https://openedx.org/openedx/sample-plugin
Project-URL: Repository, https://openedx.org/openedx/sample-plugin
Keywords: Python,edx
Classifier: Development Status :: 3 - Alpha
Classifier: Framework :: Django
Classifier: Framework :: Django :: 4.2
Classifier: Intended Audience :: Developers
Classifier: Natural Language :: English
Classifier: Programming Language :: Python :: 3
Classifier: Programming Language :: Python :: 3.12
Requires-Python: >=3.11
License-File: LICENSE.txt
Requires-Dist: Django
Requires-Dist: djangorestframework
Requires-Dist: django-filter
Requires-Dist: edx-opaque-keys
Requires-Dist: openedx-events
Requires-Dist: openedx-filters
Requires-Dist: openedx-atlas
Dynamic: license-file
